mindmate/__init__.py
mindmate/cli.py
mindmate/error.py
mindmate/meta.py
mindmate/commands/__init__.py
mindmate/commands/chat.py
mindmate/commands/configure.py
mindmate/commands/directory.py
mindmate/commands/image.py
mindmate/commands/version.py
mindmate/commands/voice.py
mindmate/services/__init__.py
mindmate/services/directory.py
mindmate/services/generic.py
mindmate/services/models.py
mindmate/services/openai.py
mindmate/services/voice.py
mindmate/utils/__init__.py
mindmate/utils/conf.py
mindmate/utils/env.py
mindmate/utils/helper.py
mindmate/utils/utils.py
mindmate-0.1.7.dist-info/LICENSE
mindmate-0.1.7.dist-info/METADATA
mindmate-0.1.7.dist-info/WHEEL
mindmate-0.1.7.dist-info/entry_points.txt
mindmate-0.1.7.dist-info/top_level.txt
mindmate-0.1.7.dist-info/RECORD
