Metadata-Version: 2.1
Name: mindmate
Version: 0.1.7
Summary: MindMate is a command-line tool that leverages the power of AI platforms to offer different use-cases to developers
Home-page: https://github.com/yalattas/mindmate
Author: Yasser Alattas
Author-email: y.alattas@gmail.com
License: LGPL-2.1 license
Download-URL: https://github.com/yalattas/mindmate
Keywords: cli,ai,nlp,ml,developers,productivity,openai,directory,manifest
Platform: any
Classifier: Development Status :: 5 - Production/Stable
Classifier: Environment :: Other Environment
Classifier: Natural Language :: English
Classifier: Programming Language :: Python
Classifier: Programming Language :: Python :: 3
Classifier: Intended Audience :: Developers
Classifier: Intended Audience :: End Users/Desktop
Classifier: Intended Audience :: Information Technology
Classifier: Intended Audience :: System Administrators
Classifier: Topic :: Software Development
Classifier: Topic :: System :: System Shells
Classifier: Topic :: Communications :: Chat
Classifier: Topic :: Internet
Classifier: Topic :: Scientific/Engineering :: Artificial Intelligence
Classifier: Topic :: Utilities
Requires-Dist: PyYAML (==6)
Requires-Dist: click (>=8)
Requires-Dist: gTTS (>=2.3)
Requires-Dist: openai (>=0.27)
Requires-Dist: requests
